pemmdb_classes/__init__.py
pemmdb_classes/classes.py
pemmdb_classes/config/__init__.py
pemmdb_classes/config/downloader/__init__.py
pemmdb_classes/config/downloader/core.py
pemmdb_classes/config/downloader/data_collection.py
pemmdb_classes/config/downloader/pivot.py
pemmdb_classes/config/downloader/post_processing.py
pemmdb_classes/config/downloader/query.py
pemmdb_classes/config/reader/__init__.py
pemmdb_classes/config/reader/data_collection.py
pemmdb_classes/config/reader/sheet.py
pemmdb_classes/cryptors/__init__.py
pemmdb_classes/cryptors/base.py
pemmdb_classes/cryptors/zaes.py
pemmdb_classes/curve/__init__.py
pemmdb_classes/curve/base.py
pemmdb_classes/curve/points.py
pemmdb_classes/curve/processors.py
pemmdb_classes/curve/table.py
pemmdb_classes/curve/timescales.py
pemmdb_classes/data_collection.py
pemmdb_classes/defaults.py
pemmdb_classes/functions/__init__.py
pemmdb_classes/raw.py
pemmdb_classes/table.py
pemmdb_classes/utils/__init__.py
pemmdb_classes/utils/clean_string.py
pemmdb_classes/utils/dumploadable.py
pemmdb_classes/version.py
pemmdb_classes-0.5.2.dist-info/METADATA
pemmdb_classes-0.5.2.dist-info/WHEEL
pemmdb_classes-0.5.2.dist-info/RECORD
