Metadata-Version: 2.1
Name: pemmdb-classes
Version: 0.5.2
Summary: PEMMDB classes to be used for downloading and manipulating PEMMDB data
Author: Christophe Druet
Author-email: christophe.druet@entsoe.eu
Requires-Python: >=3.11,<3.13
Classifier: Programming Language :: Python :: 3
Classifier: Programming Language :: Python :: 3.11
Classifier: Programming Language :: Python :: 3.12
Requires-Dist: cryptography (>=44.0.0,<45.0.0)
Requires-Dist: ez-credentials (>=1.2.3,<2.0.0)
Requires-Dist: ijson (>=3.3.0,<4.0.0)
Requires-Dist: loguru (>=0.7.3,<0.8.0)
Requires-Dist: pendulum (>=3.0.0,<4.0.0)
Requires-Dist: polars (>=1.21.0,<2.0.0)
Requires-Dist: pydantic (>=2.10.6,<3.0.0)
Requires-Dist: python-benedict (>=0.34.1,<0.35.0)
